{
  "type": "app",
  "name": "glpi",
  "id": "ddurieux-glpi-app",

  "info": {
    "description": "GLPI app for Grafana",
    "author": {
      "name": "David Durieux && DCS Easyware",
      "url": "https://github.com/ddurieux/glpi_app_grafana"
    },
    "keywords": ["glpi app","glpi","David Durieux"],
    "logos": {
      "small": "img/logo.svg",
      "large": "img/logo.svg"
    },
    "links": [
      {"name": "Project site (github)", "url": "https://github.com/ddurieux/glpi_app_grafana"},
      {"name": "License & Terms", "url": "https://raw.githubusercontent.com/ddurieux/glpi_app_grafana/master/LICENSE"},
      {"name": "Blog of David Durieux", "url": "https://david.durieux.family/"},
      {"name": "GLPI Project", "url": "http://glpi-project.org/"},
      {"name": "DCS Easyware", "url": "https://www.dcsit-group.com/"}
    ],
    "version": "2.1.0",
    "updated": "2022-10-18",
    "screenshots": [
      {"name": "dashboard", "path": "img/screenshot1.png"}
    ]
  },

  "includes": [
    {"type": "dashboard", "name": "GLPI App Dashboard", "path": "dashboards/glpi_app_dashboard.json"},
    {"type": "datasource", "name": "GLPI API"}
  ],

  "dependencies": {
    "grafanaDependency": ">=9.0.0",
    "plugins": []
  },
  "autoEnabled": true
}
